[1,["aaHT3Ppa5MfqlBWluM+HE7@6c48a"],["_textureSource"],["cc.SpriteFrame","cc.SpriteAtlas"],0,[[[{"name":"hit_eff","spriteFrames":["skill_hit10001","6dLRX+EBtP74V9PaJUO4zq@c2728","skill_hit10002","6dLRX+EBtP74V9PaJUO4zq@e6e08","skill_hit10003","6dLRX+EBtP74V9PaJUO4zq@47a6c","skill_hit10004","6dLRX+EBtP74V9PaJUO4zq@e56fa"]}],[1],0,[],[],[]],[[{"name":"skill_hit10003","rect":{"x":1,"y":226,"width":230,"height":214},"offset":{"x":0,"y":0},"originalSize":{"width":230,"height":214},"rotated":false,"capInsets":[0,0,0,0],"vertices":{"rawPosition":[],"indexes":[],"uv":[],"nuv":[],"minPos":{"x":0,"y":0,"z":0},"maxPos":{"x":0,"y":0,"z":0}},"packable":true,"pixelsToUnit":100,"pivot":{"x":0.5,"y":0.5},"meshType":0}],[0],0,[0],[0],[0]],[[{"name":"skill_hit10001","rect":{"x":1,"y":644,"width":152,"height":198},"offset":{"x":0,"y":0},"originalSize":{"width":152,"height":198},"rotated":true,"capInsets":[0,0,0,0],"vertices":{"rawPosition":[],"indexes":[],"uv":[],"nuv":[],"minPos":{"x":0,"y":0,"z":0},"maxPos":{"x":0,"y":0,"z":0}},"packable":true,"pixelsToUnit":100,"pivot":{"x":0.5,"y":0.5},"meshType":0}],[0],0,[0],[0],[0]],[[{"name":"skill_hit10004","rect":{"x":1,"y":1,"width":230,"height":224},"offset":{"x":0,"y":0},"originalSize":{"width":230,"height":224},"rotated":false,"capInsets":[0,0,0,0],"vertices":{"rawPosition":[],"indexes":[],"uv":[],"nuv":[],"minPos":{"x":0,"y":0,"z":0},"maxPos":{"x":0,"y":0,"z":0}},"packable":true,"pixelsToUnit":100,"pivot":{"x":0.5,"y":0.5},"meshType":0}],[0],0,[0],[0],[0]],[[{"name":"skill_hit10002","rect":{"x":1,"y":441,"width":226,"height":202},"offset":{"x":0,"y":0},"originalSize":{"width":226,"height":202},"rotated":false,"capInsets":[0,0,0,0],"vertices":{"rawPosition":[],"indexes":[],"uv":[],"nuv":[],"minPos":{"x":0,"y":0,"z":0},"maxPos":{"x":0,"y":0,"z":0}},"packable":true,"pixelsToUnit":100,"pivot":{"x":0.5,"y":0.5},"meshType":0}],[0],0,[0],[0],[0]]]]
